{
	"bt_bankroll_start": [
		25.0,
		25.55,
		26.1,
		26.650000000000002,
		27.200000000000003,
		27.750000000000004,
		28.300000000000004,
		28.850000000000005,
		29.400000000000006,
		29.950000000000006,
		30.500000000000007
	],
	"bt_epoch": [
		[
			"20181007",
			5
		],
		[
			"20181014",
			6
		],
		[
			"20181021",
			7
		],
		[
			"20181028",
			8
		],
		[
			"20181104",
			9
		],
		[
			"20181111",
			10
		],
		[
			"20181118",
			11
		],
		[
			"20181125",
			12
		],
		[
			"20181202",
			13
		],
		[
			"20181209",
			14
		],
		[
			"20181216",
			15
		]
	],
	"bt_total_wagered": [
		1.25,
		1.25,
		1.25,
		1.25,
		1.25,
		1.25,
		1.25,
		1.25,
		1.25,
		1.25,
		1.25
	],
	"bt_wins": [
		1,
		1,
		1,
		1,
		1,
		1,
		1,
		1,
		1,
		1,
		1
	],
	"bt_total_winnings": [
		1.8,
		1.8,
		1.8,
		1.8,
		1.8,
		1.8,
		1.8,
		1.8,
		1.8,
		1.8,
		1.8
	],
	"bt_bets": [
		[
			{
				"strategy_name": "C_gpp_25",
				"wager": 0.25,
				"bet_return": 0,
				"slate_name": "Main",
				"slate_info": {
					"style": "CLASSIC",
					"games": [
						64,
						65,
						67,
						76,
						77,
						68,
						74,
						66,
						71,
						70,
						78,
						72,
						69,
						73,
						75
					],
					"slate_id": 25,
					"name": "Main"
				},
				"actual_outcome": {
					"total_score": 276.85999999999996,
					"total_cost": 49500.0,
					"player_ids": [
						350,
						177,
						134,
						141,
						193,
						331,
						85,
						372
					],
					"player_fpts": [
						32.38,
						33.68,
						33.1,
						27.3,
						31.5,
						26.1,
						37.5,
						33.3
					],
					"player_fpts_multiplier": [
						1,
						1,
						1,
						1,
						1,
						1,
						1,
						1
					],
					"player_costs": [
						8000.0,
						6300.0,
						4100.0,
						3800.0,
						4600.0,
						3300.0,
						7500.0,
						9400.0
					],
					"player_costs_multiplier": [
						1,
						1,
						1,
						1,
						1,
						1,
						1,
						1
					],
					"team_ids": [
						18
					],
					"team_fpts": [
						22.0
					],
					"team_fpts_multiplier": [
						1
					],
					"team_costs": [
						2500.0
					],
					"team_costs_multiplier": [
						1
					],
					"placement_percentile": null
				},
				"wagered_outcome": {
					"total_score": 161.02528888791656,
					"total_cost": 50000.0,
					"player_ids": [
						512,
						222,
						328,
						370,
						187,
						272,
						47,
						224
					],
					"player_fpts": [
						20.71794070978092,
						13.499153408004352,
						27.639252850912385,
						14.697400330911602,
						15.777237505487768,
						23.895463347601723,
						10.991466372402709,
						24.220389144277632
					],
					"player_fpts_multiplier": [
						1,
						1,
						1,
						1,
						1,
						1,
						1,
						1
					],
					"player_costs": [
						4200.0,
						4200.0,
						9600.0,
						4800.0,
						5700.0,
						6000.0,
						3900.0,
						8600.0
					],
					"player_costs_multiplier": [
						1,
						1,
						1,
						1,
						1,
						1,
						1,
						1
					],
					"team_ids": [
						22
					],
					"team_fpts": [
						9.586985218537478
					],
					"team_fpts_multiplier": [
						1
					],
					"team_costs": [
						3000.0
					],
					"team_costs_multiplier": [
						1
					],
					"placement_percentile": 0.6842502215514171
				},
				"predicted_score": 151.43830366937908,
				"final_player_fpts": [
					17.3,
					12.9,
					6.9,
					6.0,
					8.4,
					18.14,
					10.5,
					22.0
				],
				"final_team_fpts": [
					0.0
				]
			},
			{
				"strategy_name": "C_5050_1",
				"wager": 1,
				"bet_return": 1.8,
				"slate_name": "Main",
				"slate_info": {
					"style": "CLASSIC",
					"games": [
						64,
						65,
						67,
						76,
						77,
						68,
						74,
						66,
						71,
						70,
						78,
						72,
						69,
						73,
						75
					],
					"slate_id": 25,
					"name": "Main"
				},
				"actual_outcome": {
					"total_score": 276.85999999999996,
					"total_cost": 49500.0,
					"player_ids": [
						350,
						177,
						134,
						141,
						193,
						331,
						85,
						372
					],
					"player_fpts": [
						32.38,
						33.68,
						33.1,
						27.3,
						31.5,
						26.1,
						37.5,
						33.3
					],
					"player_fpts_multiplier": [
						1,
						1,
						1,
						1,
						1,
						1,
						1,
						1
					],
					"player_costs": [
						8000.0,
						6300.0,
						4100.0,
						3800.0,
						4600.0,
						3300.0,
						7500.0,
						9400.0
					],
					"player_costs_multiplier": [
						1,
						1,
						1,
						1,
						1,
						1,
						1,
						1
					],
					"team_ids": [
						18
					],
					"team_fpts": [
						22.0
					],
					"team_fpts_multiplier": [
						1
					],
					"team_costs": [
						2500.0
					],
					"team_costs_multiplier": [
						1
					],
					"placement_percentile": null
				},
				"wagered_outcome": {
					"total_score": 161.02528888791656,
					"total_cost": 50000.0,
					"player_ids": [
						222,
						328,
						370,
						224,
						187,
						272,
						47,
						512
					],
					"player_fpts": [
						13.499153408004352,
						27.639252850912385,
						14.697400330911602,
						24.220389144277632,
						15.777237505487768,
						23.895463347601723,
						10.991466372402709,
						20.71794070978092
					],
					"player_fpts_multiplier": [
						1,
						1,
						1,
						1,
						1,
						1,
						1,
						1
					],
					"player_costs": [
						4200.0,
						9600.0,
						4800.0,
						8600.0,
						5700.0,
						6000.0,
						3900.0,
						4200.0
					],
					"player_costs_multiplier": [
						1,
						1,
						1,
						1,
						1,
						1,
						1,
						1
					],
					"team_ids": [
						22
					],
					"team_fpts": [
						9.586985218537478
					],
					"team_fpts_multiplier": [
						1
					],
					"team_costs": [
						3000.0
					],
					"team_costs_multiplier": [
						1
					],
					"placement_percentile": 0.6842502215514171
				},
				"predicted_score": 151.43830366937908,
				"final_player_fpts": [
					12.9,
					6.9,
					6.0,
					22.0,
					8.4,
					18.14,
					10.5,
					17.3
				],
				"final_team_fpts": [
					0.0
				]
			}
		],
		[
			{
				"strategy_name": "C_gpp_25",
				"wager": 0.25,
				"bet_return": 0,
				"slate_name": "Main",
				"slate_info": {
					"style": "CLASSIC",
					"games": [
						93,
						82,
						81,
						83,
						90,
						84,
						80,
						86,
						92,
						87,
						88,
						85,
						89,
						91,
						79
					],
					"slate_id": 26,
					"name": "Main"
				},
				"actual_outcome": {
					"total_score": 291.84000000000003,
					"total_cost": 50000.0,
					"player_ids": [
						169,
						254,
						349,
						391,
						54,
						163,
						214,
						224
					],
					"player_fpts": [
						35.2,
						33.0,
						40.900000000000006,
						22.1,
						31.1,
						31.34,
						39.2,
						38.0
					],
					"player_fpts_multiplier": [
						1,
						1,
						1,
						1,
						1,
						1,
						1,
						1
					],
					"player_costs": [
						8000.0,
						3800.0,
						7400.0,
						3500.0,
						3200.0,
						5300.0,
						7800.0,
						8200.0
					],
					"player_costs_multiplier": [
						1,
						1,
						1,
						1,
						1,
						1,
						1,
						1
					],
					"team_ids": [
						3
					],
					"team_fpts": [
						21.0
					],
					"team_fpts_multiplier": [
						1
					],
					"team_costs": [
						2800.0
					],
					"team_costs_multiplier": [
						1
					],
					"placement_percentile": null
				},
				"wagered_outcome": {
					"total_score": 149.8611050222462,
					"total_cost": 50000.0,
					"player_ids": [
						40,
						349,
						370,
						224,
						293,
						547,
						512,
						85
					],
					"player_fpts": [
						13.791640998379705,
						20.23374973035086,
						13.341995060830794,
						22.17055285921619,
						23.537253294699603,
						11.008033565283256,
						16.443126776756806,
						21.936490614142485
					],
					"player_fpts_multiplier": [
						1,
						1,
						1,
						1,
						1,
						1,
						1,
						1
					],
					"player_costs": [
						5500.0,
						7400.0,
						5000.0,
						8200.0,
						6400.0,
						3000.0,
						4600.0,
						7700.0
					],
					"player_costs_multiplier": [
						1,
						1,
						1,
						1,
						1,
						1,
						1,
						1
					],
					"team_ids": [
						27
					],
					"team_fpts": [
						7.398262122586529
					],
					"team_fpts_multiplier": [
						1
					],
					"team_costs": [
						2200.0
					],
					"team_costs_multiplier": [
						1
					],
					"placement_percentile": 0.6041227466389569
				},
				"predicted_score": 142.46284289965968,
				"final_player_fpts": [
					4.800000000000001,
					40.900000000000006,
					3.0,
					38.0,
					8.28,
					4.9,
					6.300000000000001,
					31.9
				],
				"final_team_fpts": [
					0.0
				]
			},
			{
				"strategy_name": "C_5050_1",
				"wager": 1,
				"bet_return": 1.8,
				"slate_name": "Main",
				"slate_info": {
					"style": "CLASSIC",
					"games": [
						93,
						82,
						81,
						83,
						90,
						84,
						80,
						86,
						92,
						87,
						88,
						85,
						89,
						91,
						79
					],
					"slate_id": 26,
					"name": "Main"
				},
				"actual_outcome": {
					"total_score": 291.84000000000003,
					"total_cost": 50000.0,
					"player_ids": [
						169,
						254,
						349,
						391,
						214,
						163,
						54,
						224
					],
					"player_fpts": [
						35.2,
						33.0,
						40.900000000000006,
						22.1,
						39.2,
						31.34,
						31.1,
						38.0
					],
					"player_fpts_multiplier": [
						1,
						1,
						1,
						1,
						1,
						1,
						1,
						1
					],
					"player_costs": [
						8000.0,
						3800.0,
						7400.0,
						3500.0,
						7800.0,
						5300.0,
						3200.0,
						8200.0
					],
					"player_costs_multiplier": [
						1,
						1,
						1,
						1,
						1,
						1,
						1,
						1
					],
					"team_ids": [
						3
					],
					"team_fpts": [
						21.0
					],
					"team_fpts_multiplier": [
						1
					],
					"team_costs": [
						2800.0
					],
					"team_costs_multiplier": [
						1
					],
					"placement_percentile": null
				},
				"wagered_outcome": {
					"total_score": 149.8611050222462,
					"total_cost": 50000.0,
					"player_ids": [
						512,
						40,
						349,
						370,
						293,
						547,
						224,
						85
					],
					"player_fpts": [
						16.443126776756806,
						13.791640998379705,
						20.23374973035086,
						13.341995060830794,
						23.537253294699603,
						11.008033565283256,
						22.17055285921619,
						21.936490614142485
					],
					"player_fpts_multiplier": [
						1,
						1,
						1,
						1,
						1,
						1,
						1,
						1
					],
					"player_costs": [
						4600.0,
						5500.0,
						7400.0,
						5000.0,
						6400.0,
						3000.0,
						8200.0,
						7700.0
					],
					"player_costs_multiplier": [
						1,
						1,
						1,
						1,
						1,
						1,
						1,
						1
					],
					"team_ids": [
						27
					],
					"team_fpts": [
						7.398262122586529
					],
					"team_fpts_multiplier": [
						1
					],
					"team_costs": [
						2200.0
					],
					"team_costs_multiplier": [
						1
					],
					"placement_percentile": 0.6041227466389569
				},
				"predicted_score": 142.46284289965968,
				"final_player_fpts": [
					6.300000000000001,
					4.800000000000001,
					40.900000000000006,
					3.0,
					8.28,
					4.9,
					38.0,
					31.9
				],
				"final_team_fpts": [
					0.0
				]
			}
		],
		[
			{
				"strategy_name": "C_gpp_25",
				"wager": 0.25,
				"bet_return": 0,
				"slate_name": "Main",
				"slate_info": {
					"style": "CLASSIC",
					"games": [
						94,
						107,
						96,
						103,
						97,
						98,
						101,
						100,
						102,
						105,
						106,
						99,
						104,
						95
					],
					"slate_id": 27,
					"name": "Main"
				},
				"actual_outcome": {
					"total_score": 273.04,
					"total_cost": 49300.0,
					"player_ids": [
						350,
						307,
						168,
						124,
						465,
						230,
						218,
						163
					],
					"player_fpts": [
						28.200000000000003,
						29.700000000000003,
						27.6,
						27.32,
						34.9,
						21.8,
						37.1,
						36.42
					],
					"player_fpts_multiplier": [
						1,
						1,
						1,
						1,
						1,
						1,
						1,
						1
					],
					"player_costs": [
						8100.0,
						6900.0,
						4300.0,
						6500.0,
						4400.0,
						3800.0,
						6800.0,
						5600.0
					],
					"player_costs_multiplier": [
						1,
						1,
						1,
						1,
						1,
						1,
						1,
						1
					],
					"team_ids": [
						9
					],
					"team_fpts": [
						30.0
					],
					"team_fpts_multiplier": [
						1
					],
					"team_costs": [
						2900.0
					],
					"team_costs_multiplier": [
						1
					],
					"placement_percentile": null
				},
				"wagered_outcome": {
					"total_score": 147.75404408119024,
					"total_cost": 50000.0,
					"player_ids": [
						254,
						328,
						349,
						560,
						197,
						568,
						512,
						372
					],
					"player_fpts": [
						12.465890107526787,
						22.752188459716482,
						22.052406381713986,
						13.539811115264943,
						23.274884941308834,
						9.513877146343956,
						13.132984171823216,
						23.74011620052446
					],
					"player_fpts_multiplier": [
						1,
						1,
						1,
						1,
						1,
						1,
						1,
						1
					],
					"player_costs": [
						4000.0,
						8500.0,
						8900.0,
						3600.0,
						6200.0,
						2600.0,
						4300.0,
						9800.0
					],
					"player_costs_multiplier": [
						1,
						1,
						1,
						1,
						1,
						1,
						1,
						1
					],
					"team_ids": [
						12
					],
					"team_fpts": [
						7.281885556967589
					],
					"team_fpts_multiplier": [
						1
					],
					"team_costs": [
						2100.0
					],
					"team_costs_multiplier": [
						1
					],
					"placement_percentile": 0.6366403719394282
				},
				"predicted_score": 140.47215852422266,
				"final_player_fpts": [
					6.6,
					15.5,
					26.4,
					5.300000000000001,
					22.740000000000002,
					4.300000000000001,
					1.3,
					30.6
				],
				"final_team_fpts": [
					-3.0
				]
			},
			{
				"strategy_name": "C_5050_1",
				"wager": 1,
				"bet_return": 1.8,
				"slate_name": "Main",
				"slate_info": {
					"style": "CLASSIC",
					"games": [
						94,
						107,
						96,
						103,
						97,
						98,
						101,
						100,
						102,
						105,
						106,
						99,
						104,
						95
					],
					"slate_id": 27,
					"name": "Main"
				},
				"actual_outcome": {
					"total_score": 273.04,
					"total_cost": 49300.0,
					"player_ids": [
						350,
						307,
						168,
						124,
						465,
						230,
						218,
						163
					],
					"player_fpts": [
						28.200000000000003,
						29.700000000000003,
						27.6,
						27.32,
						34.9,
						21.8,
						37.1,
						36.42
					],
					"player_fpts_multiplier": [
						1,
						1,
						1,
						1,
						1,
						1,
						1,
						1
					],
					"player_costs": [
						8100.0,
						6900.0,
						4300.0,
						6500.0,
						4400.0,
						3800.0,
						6800.0,
						5600.0
					],
					"player_costs_multiplier": [
						1,
						1,
						1,
						1,
						1,
						1,
						1,
						1
					],
					"team_ids": [
						9
					],
					"team_fpts": [
						30.0
					],
					"team_fpts_multiplier": [
						1
					],
					"team_costs": [
						2900.0
					],
					"team_costs_multiplier": [
						1
					],
					"placement_percentile": null
				},
				"wagered_outcome": {
					"total_score": 147.75404408119024,
					"total_cost": 50000.0,
					"player_ids": [
						254,
						328,
						349,
						560,
						197,
						568,
						512,
						372
					],
					"player_fpts": [
						12.465890107526787,
						22.752188459716482,
						22.052406381713986,
						13.539811115264943,
						23.274884941308834,
						9.513877146343956,
						13.132984171823216,
						23.74011620052446
					],
					"player_fpts_multiplier": [
						1,
						1,
						1,
						1,
						1,
						1,
						1,
						1
					],
					"player_costs": [
						4000.0,
						8500.0,
						8900.0,
						3600.0,
						6200.0,
						2600.0,
						4300.0,
						9800.0
					],
					"player_costs_multiplier": [
						1,
						1,
						1,
						1,
						1,
						1,
						1,
						1
					],
					"team_ids": [
						12
					],
					"team_fpts": [
						7.281885556967589
					],
					"team_fpts_multiplier": [
						1
					],
					"team_costs": [
						2100.0
					],
					"team_costs_multiplier": [
						1
					],
					"placement_percentile": 0.6366403719394282
				},
				"predicted_score": 140.47215852422266,
				"final_player_fpts": [
					6.6,
					15.5,
					26.4,
					5.300000000000001,
					22.740000000000002,
					4.300000000000001,
					1.3,
					30.6
				],
				"final_team_fpts": [
					-3.0
				]
			}
		],
		[
			{
				"strategy_name": "C_gpp_25",
				"wager": 0.25,
				"bet_return": 0,
				"slate_name": "Main",
				"slate_info": {
					"style": "CLASSIC",
					"games": [
						108,
						109,
						110,
						121,
						113,
						111,
						112,
						116,
						118,
						114,
						119,
						115,
						120,
						117
					],
					"slate_id": 28,
					"name": "Main"
				},
				"actual_outcome": {
					"total_score": 268.46,
					"total_cost": 49800.0,
					"player_ids": [
						285,
						146,
						465,
						187,
						293,
						217,
						85,
						372
					],
					"player_fpts": [
						18.9,
						30.700000000000003,
						31.9,
						28.6,
						30.96,
						30.700000000000003,
						41.2,
						36.5
					],
					"player_fpts_multiplier": [
						1,
						1,
						1,
						1,
						1,
						1,
						1,
						1
					],
					"player_costs": [
						2500.0,
						4800.0,
						5400.0,
						6700.0,
						6000.0,
						4600.0,
						7500.0,
						9800.0
					],
					"player_costs_multiplier": [
						1,
						1,
						1,
						1,
						1,
						1,
						1,
						1
					],
					"team_ids": [
						16
					],
					"team_fpts": [
						19.0
					],
					"team_fpts_multiplier": [
						1
					],
					"team_costs": [
						2500.0
					],
					"team_costs_multiplier": [
						1
					],
					"placement_percentile": null
				},
				"wagered_outcome": {
					"total_score": 150.85846053503298,
					"total_cost": 50000.0,
					"player_ids": [
						328,
						124,
						465,
						163,
						193,
						171,
						85,
						42
					],
					"player_fpts": [
						22.090495489924812,
						16.573594468560167,
						15.509007503165122,
						24.80598395415212,
						13.826215585558122,
						13.219527334532113,
						23.079777954819612,
						13.750382992524045
					],
					"player_fpts_multiplier": [
						1,
						1,
						1,
						1,
						1,
						1,
						1,
						1
					],
					"player_costs": [
						7400.0,
						6500.0,
						5400.0,
						6100.0,
						4900.0,
						4900.0,
						7500.0,
						4800.0
					],
					"player_costs_multiplier": [
						1,
						1,
						1,
						1,
						1,
						1,
						1,
						1
					],
					"team_ids": [
						22
					],
					"team_fpts": [
						8.00347525179685
					],
					"team_fpts_multiplier": [
						1
					],
					"team_costs": [
						2500.0
					],
					"team_costs_multiplier": [
						1
					],
					"placement_percentile": 0.6611060932947969
				},
				"predicted_score": 142.85498528323612,
				"final_player_fpts": [
					26.6,
					9.100000000000001,
					31.9,
					21.900000000000002,
					12.7,
					8.0,
					41.2,
					6.1
				],
				"final_team_fpts": [
					8.0
				]
			},
			{
				"strategy_name": "C_5050_1",
				"wager": 1,
				"bet_return": 1.8,
				"slate_name": "Main",
				"slate_info": {
					"style": "CLASSIC",
					"games": [
						108,
						109,
						110,
						121,
						113,
						111,
						112,
						116,
						118,
						114,
						119,
						115,
						120,
						117
					],
					"slate_id": 28,
					"name": "Main"
				},
				"actual_outcome": {
					"total_score": 268.46000000000004,
					"total_cost": 49800.0,
					"player_ids": [
						85,
						285,
						146,
						465,
						187,
						293,
						217,
						372
					],
					"player_fpts": [
						41.2,
						18.9,
						30.700000000000003,
						31.9,
						28.6,
						30.96,
						30.700000000000003,
						36.5
					],
					"player_fpts_multiplier": [
						1,
						1,
						1,
						1,
						1,
						1,
						1,
						1
					],
					"player_costs": [
						7500.0,
						2500.0,
						4800.0,
						5400.0,
						6700.0,
						6000.0,
						4600.0,
						9800.0
					],
					"player_costs_multiplier": [
						1,
						1,
						1,
						1,
						1,
						1,
						1,
						1
					],
					"team_ids": [
						16
					],
					"team_fpts": [
						19.0
					],
					"team_fpts_multiplier": [
						1
					],
					"team_costs": [
						2500.0
					],
					"team_costs_multiplier": [
						1
					],
					"placement_percentile": null
				},
				"wagered_outcome": {
					"total_score": 150.85846053503298,
					"total_cost": 50000.0,
					"player_ids": [
						328,
						124,
						465,
						163,
						193,
						171,
						85,
						42
					],
					"player_fpts": [
						22.090495489924812,
						16.573594468560167,
						15.509007503165122,
						24.80598395415212,
						13.826215585558122,
						13.219527334532113,
						23.079777954819612,
						13.750382992524045
					],
					"player_fpts_multiplier": [
						1,
						1,
						1,
						1,
						1,
						1,
						1,
						1
					],
					"player_costs": [
						7400.0,
						6500.0,
						5400.0,
						6100.0,
						4900.0,
						4900.0,
						7500.0,
						4800.0
					],
					"player_costs_multiplier": [
						1,
						1,
						1,
						1,
						1,
						1,
						1,
						1
					],
					"team_ids": [
						22
					],
					"team_fpts": [
						8.00347525179685
					],
					"team_fpts_multiplier": [
						1
					],
					"team_costs": [
						2500.0
					],
					"team_costs_multiplier": [
						1
					],
					"placement_percentile": 0.6611060932947969
				},
				"predicted_score": 142.85498528323612,
				"final_player_fpts": [
					26.6,
					9.100000000000001,
					31.9,
					21.900000000000002,
					12.7,
					8.0,
					41.2,
					6.1
				],
				"final_team_fpts": [
					8.0
				]
			}
		],
		[
			{
				"strategy_name": "C_gpp_25",
				"wager": 0.25,
				"bet_return": 0,
				"slate_name": "Main",
				"slate_info": {
					"style": "CLASSIC",
					"games": [
						134,
						122,
						123,
						124,
						126,
						125,
						127,
						132,
						128,
						129,
						133,
						130,
						131
					],
					"slate_id": 29,
					"name": "Main"
				},
				"actual_outcome": {
					"total_score": 278.03999999999996,
					"total_cost": 49800.0,
					"player_ids": [
						318,
						328,
						218,
						323,
						547,
						215,
						332,
						385
					],
					"player_fpts": [
						28.9,
						33.6,
						33.1,
						34.440000000000005,
						22.4,
						28.9,
						39.1,
						32.6
					],
					"player_fpts_multiplier": [
						1,
						1,
						1,
						1,
						1,
						1,
						1,
						1
					],
					"player_costs": [
						3600.0,
						7300.0,
						7700.0,
						6100.0,
						3300.0,
						6600.0,
						7600.0,
						4800.0
					],
					"player_costs_multiplier": [
						1,
						1,
						1,
						1,
						1,
						1,
						1,
						1
					],
					"team_ids": [
						19
					],
					"team_fpts": [
						25.0
					],
					"team_fpts_multiplier": [
						1
					],
					"team_costs": [
						2800.0
					],
					"team_costs_multiplier": [
						1
					],
					"placement_percentile": null
				},
				"wagered_outcome": {
					"total_score": 142.82395576161045,
					"total_cost": 49900.0,
					"player_ids": [
						328,
						71,
						124,
						47,
						333,
						171,
						224,
						85
					],
					"player_fpts": [
						20.46708788326947,
						24.395737991796686,
						14.911590426291237,
						11.499329889978007,
						9.457462023834111,
						11.8354018378319,
						21.586254171519077,
						21.351822391646085
					],
					"player_fpts_multiplier": [
						1,
						1,
						1,
						1,
						1,
						1,
						1,
						1
					],
					"player_costs": [
						7300.0,
						6600.0,
						6400.0,
						4200.0,
						3200.0,
						4600.0,
						8200.0,
						7200.0
					],
					"player_costs_multiplier": [
						1,
						1,
						1,
						1,
						1,
						1,
						1,
						1
					],
					"team_ids": [
						23
					],
					"team_fpts": [
						7.319269145443878
					],
					"team_fpts_multiplier": [
						1
					],
					"team_costs": [
						2200.0
					],
					"team_costs_multiplier": [
						1
					],
					"placement_percentile": 0.6043309712593636
				},
				"predicted_score": 135.50468661616657,
				"final_player_fpts": [
					33.6,
					21.180000000000003,
					10.7,
					12.8,
					15.2,
					7.4,
					22.3,
					32.3
				],
				"final_team_fpts": [
					4.0
				]
			},
			{
				"strategy_name": "C_5050_1",
				"wager": 1,
				"bet_return": 1.8,
				"slate_name": "Main",
				"slate_info": {
					"style": "CLASSIC",
					"games": [
						134,
						122,
						123,
						124,
						126,
						125,
						127,
						132,
						128,
						129,
						133,
						130,
						131
					],
					"slate_id": 29,
					"name": "Main"
				},
				"actual_outcome": {
					"total_score": 278.03999999999996,
					"total_cost": 49800.0,
					"player_ids": [
						318,
						328,
						218,
						547,
						323,
						215,
						332,
						385
					],
					"player_fpts": [
						28.9,
						33.6,
						33.1,
						22.4,
						34.440000000000005,
						28.9,
						39.1,
						32.6
					],
					"player_fpts_multiplier": [
						1,
						1,
						1,
						1,
						1,
						1,
						1,
						1
					],
					"player_costs": [
						3600.0,
						7300.0,
						7700.0,
						3300.0,
						6100.0,
						6600.0,
						7600.0,
						4800.0
					],
					"player_costs_multiplier": [
						1,
						1,
						1,
						1,
						1,
						1,
						1,
						1
					],
					"team_ids": [
						19
					],
					"team_fpts": [
						25.0
					],
					"team_fpts_multiplier": [
						1
					],
					"team_costs": [
						2800.0
					],
					"team_costs_multiplier": [
						1
					],
					"placement_percentile": null
				},
				"wagered_outcome": {
					"total_score": 142.82395576161045,
					"total_cost": 49900.0,
					"player_ids": [
						328,
						71,
						124,
						47,
						333,
						171,
						224,
						85
					],
					"player_fpts": [
						20.46708788326947,
						24.395737991796686,
						14.911590426291237,
						11.499329889978007,
						9.457462023834111,
						11.8354018378319,
						21.586254171519077,
						21.351822391646085
					],
					"player_fpts_multiplier": [
						1,
						1,
						1,
						1,
						1,
						1,
						1,
						1
					],
					"player_costs": [
						7300.0,
						6600.0,
						6400.0,
						4200.0,
						3200.0,
						4600.0,
						8200.0,
						7200.0
					],
					"player_costs_multiplier": [
						1,
						1,
						1,
						1,
						1,
						1,
						1,
						1
					],
					"team_ids": [
						23
					],
					"team_fpts": [
						7.319269145443878
					],
					"team_fpts_multiplier": [
						1
					],
					"team_costs": [
						2200.0
					],
					"team_costs_multiplier": [
						1
					],
					"placement_percentile": 0.6043309712593636
				},
				"predicted_score": 135.50468661616657,
				"final_player_fpts": [
					33.6,
					21.180000000000003,
					10.7,
					12.8,
					15.2,
					7.4,
					22.3,
					32.3
				],
				"final_team_fpts": [
					4.0
				]
			}
		],
		[
			{
				"strategy_name": "C_gpp_25",
				"wager": 0.25,
				"bet_return": 0,
				"slate_name": "Main",
				"slate_info": {
					"style": "CLASSIC",
					"games": [
						137,
						145,
						142,
						138,
						135,
						139,
						136,
						140,
						148,
						146,
						147,
						143,
						141,
						144
					],
					"slate_id": 30,
					"name": "Main"
				},
				"actual_outcome": {
					"total_score": 299.8,
					"total_cost": 49700.0,
					"player_ids": [
						241,
						164,
						163,
						397,
						87,
						214,
						501,
						63
					],
					"player_fpts": [
						25.5,
						31.3,
						39.0,
						40.5,
						38.900000000000006,
						32.7,
						35.2,
						39.7
					],
					"player_fpts_multiplier": [
						1,
						1,
						1,
						1,
						1,
						1,
						1,
						1
					],
					"player_costs": [
						4500.0,
						5000.0,
						5600.0,
						6300.0,
						5500.0,
						7300.0,
						5000.0,
						7500.0
					],
					"player_costs_multiplier": [
						1,
						1,
						1,
						1,
						1,
						1,
						1,
						1
					],
					"team_ids": [
						2
					],
					"team_fpts": [
						17.0
					],
					"team_fpts_multiplier": [
						1
					],
					"team_costs": [
						3000.0
					],
					"team_costs_multiplier": [
						1
					],
					"placement_percentile": null
				},
				"wagered_outcome": {
					"total_score": 147.81463571958253,
					"total_cost": 50000.0,
					"player_ids": [
						318,
						200,
						328,
						602,
						386,
						193,
						85,
						372
					],
					"player_fpts": [
						11.708562169972073,
						11.166485452116163,
						21.666951166937977,
						10.838617745036167,
						22.79783847910104,
						13.23260914517576,
						22.942713601592928,
						23.897680422872483
					],
					"player_fpts_multiplier": [
						1,
						1,
						1,
						1,
						1,
						1,
						1,
						1
					],
					"player_costs": [
						3900.0,
						3700.0,
						8700.0,
						3000.0,
						6200.0,
						3500.0,
						8300.0,
						9400.0
					],
					"player_costs_multiplier": [
						1,
						1,
						1,
						1,
						1,
						1,
						1,
						1
					],
					"team_ids": [
						18
					],
					"team_fpts": [
						9.563177536777939
					],
					"team_fpts_multiplier": [
						1
					],
					"team_costs": [
						3300.0
					],
					"team_costs_multiplier": [
						1
					],
					"placement_percentile": 0.5800519394089492
				},
				"predicted_score": 138.25145818280458,
				"final_player_fpts": [
					7.300000000000001,
					-0.4,
					26.200000000000003,
					8.100000000000001,
					24.500000000000004,
					28.1,
					14.3,
					28.0
				],
				"final_team_fpts": [
					10.0
				]
			},
			{
				"strategy_name": "C_5050_1",
				"wager": 1,
				"bet_return": 1.8,
				"slate_name": "Main",
				"slate_info": {
					"style": "CLASSIC",
					"games": [
						137,
						145,
						142,
						138,
						135,
						139,
						136,
						140,
						148,
						146,
						147,
						143,
						141,
						144
					],
					"slate_id": 30,
					"name": "Main"
				},
				"actual_outcome": {
					"total_score": 299.8,
					"total_cost": 49700.0,
					"player_ids": [
						241,
						164,
						163,
						397,
						87,
						214,
						501,
						63
					],
					"player_fpts": [
						25.5,
						31.3,
						39.0,
						40.5,
						38.900000000000006,
						32.7,
						35.2,
						39.7
					],
					"player_fpts_multiplier": [
						1,
						1,
						1,
						1,
						1,
						1,
						1,
						1
					],
					"player_costs": [
						4500.0,
						5000.0,
						5600.0,
						6300.0,
						5500.0,
						7300.0,
						5000.0,
						7500.0
					],
					"player_costs_multiplier": [
						1,
						1,
						1,
						1,
						1,
						1,
						1,
						1
					],
					"team_ids": [
						2
					],
					"team_fpts": [
						17.0
					],
					"team_fpts_multiplier": [
						1
					],
					"team_costs": [
						3000.0
					],
					"team_costs_multiplier": [
						1
					],
					"placement_percentile": null
				},
				"wagered_outcome": {
					"total_score": 147.81463571958253,
					"total_cost": 50000.0,
					"player_ids": [
						318,
						200,
						328,
						602,
						386,
						193,
						85,
						372
					],
					"player_fpts": [
						11.708562169972073,
						11.166485452116163,
						21.666951166937977,
						10.838617745036167,
						22.79783847910104,
						13.23260914517576,
						22.942713601592928,
						23.897680422872483
					],
					"player_fpts_multiplier": [
						1,
						1,
						1,
						1,
						1,
						1,
						1,
						1
					],
					"player_costs": [
						3900.0,
						3700.0,
						8700.0,
						3000.0,
						6200.0,
						3500.0,
						8300.0,
						9400.0
					],
					"player_costs_multiplier": [
						1,
						1,
						1,
						1,
						1,
						1,
						1,
						1
					],
					"team_ids": [
						18
					],
					"team_fpts": [
						9.563177536777939
					],
					"team_fpts_multiplier": [
						1
					],
					"team_costs": [
						3300.0
					],
					"team_costs_multiplier": [
						1
					],
					"placement_percentile": 0.5800519394089492
				},
				"predicted_score": 138.25145818280458,
				"final_player_fpts": [
					7.300000000000001,
					-0.4,
					26.200000000000003,
					8.100000000000001,
					24.500000000000004,
					28.1,
					14.3,
					28.0
				],
				"final_team_fpts": [
					10.0
				]
			}
		],
		[
			{
				"strategy_name": "C_gpp_25",
				"wager": 0.25,
				"bet_return": 0,
				"slate_name": "Main",
				"slate_info": {
					"style": "CLASSIC",
					"games": [
						149,
						161,
						151,
						160,
						153,
						152,
						154,
						157,
						158,
						159,
						155,
						156,
						150
					],
					"slate_id": 31,
					"name": "Main"
				},
				"actual_outcome": {
					"total_score": 292.71999999999997,
					"total_cost": 50000.0,
					"player_ids": [
						349,
						209,
						70,
						571,
						195,
						215,
						214,
						331
					],
					"player_fpts": [
						38.2,
						43.92,
						28.700000000000003,
						22.5,
						36.5,
						28.700000000000003,
						43.5,
						31.700000000000003
					],
					"player_fpts_multiplier": [
						1,
						1,
						1,
						1,
						1,
						1,
						1,
						1
					],
					"player_costs": [
						8700.0,
						7100.0,
						4200.0,
						3000.0,
						6100.0,
						6500.0,
						8300.0,
						4000.0
					],
					"player_costs_multiplier": [
						1,
						1,
						1,
						1,
						1,
						1,
						1,
						1
					],
					"team_ids": [
						30
					],
					"team_fpts": [
						19.0
					],
					"team_fpts_multiplier": [
						1
					],
					"team_costs": [
						2100.0
					],
					"team_costs_multiplier": [
						1
					],
					"placement_percentile": null
				},
				"wagered_outcome": {
					"total_score": 145.78720676220232,
					"total_cost": 50000.0,
					"player_ids": [
						349,
						602,
						47,
						386,
						193,
						512,
						85,
						372
					],
					"player_fpts": [
						22.46826405153194,
						9.302034355686446,
						12.06046819028408,
						22.699593450804013,
						13.775046989224109,
						11.648628128486898,
						22.028094456870136,
						24.161926635065292
					],
					"player_fpts_multiplier": [
						1,
						1,
						1,
						1,
						1,
						1,
						1,
						1
					],
					"player_costs": [
						8700.0,
						3200.0,
						4300.0,
						6100.0,
						4300.0,
						4500.0,
						7200.0,
						9600.0
					],
					"player_costs_multiplier": [
						1,
						1,
						1,
						1,
						1,
						1,
						1,
						1
					],
					"team_ids": [
						25
					],
					"team_fpts": [
						7.643150504249417
					],
					"team_fpts_multiplier": [
						1
					],
					"team_costs": [
						2100.0
					],
					"team_costs_multiplier": [
						1
					],
					"placement_percentile": 0.5859331815274277
				},
				"predicted_score": 138.1440562579529,
				"final_player_fpts": [
					38.2,
					13.4,
					10.100000000000001,
					14.74,
					0.0,
					12.7,
					10.9,
					12.4
				],
				"final_team_fpts": [
					13.0
				]
			},
			{
				"strategy_name": "C_5050_1",
				"wager": 1,
				"bet_return": 1.8,
				"slate_name": "Main",
				"slate_info": {
					"style": "CLASSIC",
					"games": [
						149,
						161,
						151,
						160,
						153,
						152,
						154,
						157,
						158,
						159,
						155,
						156,
						150
					],
					"slate_id": 31,
					"name": "Main"
				},
				"actual_outcome": {
					"total_score": 292.71999999999997,
					"total_cost": 50000.0,
					"player_ids": [
						349,
						209,
						70,
						571,
						195,
						215,
						214,
						331
					],
					"player_fpts": [
						38.2,
						43.92,
						28.700000000000003,
						22.5,
						36.5,
						28.700000000000003,
						43.5,
						31.700000000000003
					],
					"player_fpts_multiplier": [
						1,
						1,
						1,
						1,
						1,
						1,
						1,
						1
					],
					"player_costs": [
						8700.0,
						7100.0,
						4200.0,
						3000.0,
						6100.0,
						6500.0,
						8300.0,
						4000.0
					],
					"player_costs_multiplier": [
						1,
						1,
						1,
						1,
						1,
						1,
						1,
						1
					],
					"team_ids": [
						30
					],
					"team_fpts": [
						19.0
					],
					"team_fpts_multiplier": [
						1
					],
					"team_costs": [
						2100.0
					],
					"team_costs_multiplier": [
						1
					],
					"placement_percentile": null
				},
				"wagered_outcome": {
					"total_score": 145.78720676220232,
					"total_cost": 50000.0,
					"player_ids": [
						349,
						602,
						47,
						386,
						193,
						512,
						85,
						372
					],
					"player_fpts": [
						22.46826405153194,
						9.302034355686446,
						12.06046819028408,
						22.699593450804013,
						13.775046989224109,
						11.648628128486898,
						22.028094456870136,
						24.161926635065292
					],
					"player_fpts_multiplier": [
						1,
						1,
						1,
						1,
						1,
						1,
						1,
						1
					],
					"player_costs": [
						8700.0,
						3200.0,
						4300.0,
						6100.0,
						4300.0,
						4500.0,
						7200.0,
						9600.0
					],
					"player_costs_multiplier": [
						1,
						1,
						1,
						1,
						1,
						1,
						1,
						1
					],
					"team_ids": [
						25
					],
					"team_fpts": [
						7.643150504249417
					],
					"team_fpts_multiplier": [
						1
					],
					"team_costs": [
						2100.0
					],
					"team_costs_multiplier": [
						1
					],
					"placement_percentile": 0.5859331815274277
				},
				"predicted_score": 138.1440562579529,
				"final_player_fpts": [
					38.2,
					13.4,
					10.100000000000001,
					14.74,
					0.0,
					12.7,
					10.9,
					12.4
				],
				"final_team_fpts": [
					13.0
				]
			}
		],
		[
			{
				"strategy_name": "C_gpp_25",
				"wager": 0.25,
				"bet_return": 0,
				"slate_name": "Main",
				"slate_info": {
					"style": "CLASSIC",
					"games": [
						162,
						163,
						164,
						166,
						167,
						168,
						174,
						170,
						165,
						171,
						172,
						169,
						173,
						176,
						175
					],
					"slate_id": 32,
					"name": "Main"
				},
				"actual_outcome": {
					"total_score": 275.28,
					"total_cost": 49400.0,
					"player_ids": [
						222,
						371,
						349,
						272,
						69,
						122,
						193,
						84
					],
					"player_fpts": [
						26.3,
						38.0,
						36.2,
						30.38,
						49.7,
						20.3,
						21.5,
						37.900000000000006
					],
					"player_fpts_multiplier": [
						1,
						1,
						1,
						1,
						1,
						1,
						1,
						1
					],
					"player_costs": [
						3700.0,
						5700.0,
						9100.0,
						5500.0,
						7900.0,
						3700.0,
						4000.0,
						7500.0
					],
					"player_costs_multiplier": [
						1,
						1,
						1,
						1,
						1,
						1,
						1,
						1
					],
					"team_ids": [
						25
					],
					"team_fpts": [
						15.0
					],
					"team_fpts_multiplier": [
						1
					],
					"team_costs": [
						2300.0
					],
					"team_costs_multiplier": [
						1
					],
					"placement_percentile": null
				},
				"wagered_outcome": {
					"total_score": 144.8332467461792,
					"total_cost": 50000.0,
					"player_ids": [
						85,
						349,
						224,
						22,
						246,
						512,
						53,
						95
					],
					"player_fpts": [
						21.694641042408094,
						22.677598677456636,
						23.083423285607026,
						10.763760817335092,
						13.887159965059139,
						12.520428377362515,
						20.053773989052303,
						10.858044620455033
					],
					"player_fpts_multiplier": [
						1,
						1,
						1,
						1,
						1,
						1,
						1,
						1
					],
					"player_costs": [
						7800.0,
						9100.0,
						8600.0,
						3400.0,
						4600.0,
						4600.0,
						5100.0,
						3800.0
					],
					"player_costs_multiplier": [
						1,
						1,
						1,
						1,
						1,
						1,
						1,
						1
					],
					"team_ids": [
						24
					],
					"team_fpts": [
						9.294415971443346
					],
					"team_fpts_multiplier": [
						1
					],
					"team_costs": [
						3000.0
					],
					"team_costs_multiplier": [
						1
					],
					"placement_percentile": 0.6189772413379284
				},
				"predicted_score": 135.53883077473586,
				"final_player_fpts": [
					12.5,
					36.2,
					20.6,
					0.0,
					2.3,
					3.4000000000000004,
					27.360000000000003,
					17.3
				],
				"final_team_fpts": [
					9.0
				]
			},
			{
				"strategy_name": "C_5050_1",
				"wager": 1,
				"bet_return": 1.8,
				"slate_name": "Main",
				"slate_info": {
					"style": "CLASSIC",
					"games": [
						162,
						163,
						164,
						166,
						167,
						168,
						174,
						170,
						165,
						171,
						172,
						169,
						173,
						176,
						175
					],
					"slate_id": 32,
					"name": "Main"
				},
				"actual_outcome": {
					"total_score": 275.28,
					"total_cost": 49400.0,
					"player_ids": [
						222,
						371,
						349,
						272,
						69,
						122,
						193,
						84
					],
					"player_fpts": [
						26.3,
						38.0,
						36.2,
						30.38,
						49.7,
						20.3,
						21.5,
						37.900000000000006
					],
					"player_fpts_multiplier": [
						1,
						1,
						1,
						1,
						1,
						1,
						1,
						1
					],
					"player_costs": [
						3700.0,
						5700.0,
						9100.0,
						5500.0,
						7900.0,
						3700.0,
						4000.0,
						7500.0
					],
					"player_costs_multiplier": [
						1,
						1,
						1,
						1,
						1,
						1,
						1,
						1
					],
					"team_ids": [
						25
					],
					"team_fpts": [
						15.0
					],
					"team_fpts_multiplier": [
						1
					],
					"team_costs": [
						2300.0
					],
					"team_costs_multiplier": [
						1
					],
					"placement_percentile": null
				},
				"wagered_outcome": {
					"total_score": 144.8332467461792,
					"total_cost": 50000.0,
					"player_ids": [
						512,
						349,
						246,
						22,
						53,
						224,
						85,
						95
					],
					"player_fpts": [
						12.520428377362515,
						22.677598677456636,
						13.887159965059139,
						10.763760817335092,
						20.053773989052303,
						23.083423285607026,
						21.694641042408094,
						10.858044620455033
					],
					"player_fpts_multiplier": [
						1,
						1,
						1,
						1,
						1,
						1,
						1,
						1
					],
					"player_costs": [
						4600.0,
						9100.0,
						4600.0,
						3400.0,
						5100.0,
						8600.0,
						7800.0,
						3800.0
					],
					"player_costs_multiplier": [
						1,
						1,
						1,
						1,
						1,
						1,
						1,
						1
					],
					"team_ids": [
						24
					],
					"team_fpts": [
						9.294415971443346
					],
					"team_fpts_multiplier": [
						1
					],
					"team_costs": [
						3000.0
					],
					"team_costs_multiplier": [
						1
					],
					"placement_percentile": 0.6189772413379284
				},
				"predicted_score": 135.53883077473586,
				"final_player_fpts": [
					3.4000000000000004,
					36.2,
					2.3,
					0.0,
					27.360000000000003,
					20.6,
					12.5,
					17.3
				],
				"final_team_fpts": [
					9.0
				]
			}
		],
		[
			{
				"strategy_name": "C_gpp_25",
				"wager": 0.25,
				"bet_return": 0,
				"slate_name": "Main",
				"slate_info": {
					"style": "CLASSIC",
					"games": [
						179,
						189,
						190,
						180,
						181,
						178,
						184,
						192,
						185,
						182,
						191,
						186,
						183,
						187,
						188,
						177
					],
					"slate_id": 33,
					"name": "Main"
				},
				"actual_outcome": {
					"total_score": 283.78000000000003,
					"total_cost": 49900.0,
					"player_ids": [
						220,
						261,
						120,
						162,
						215,
						22,
						31,
						372
					],
					"player_fpts": [
						36.8,
						29.700000000000003,
						31.9,
						34.64,
						39.8,
						24.7,
						33.74,
						34.5
					],
					"player_fpts_multiplier": [
						1,
						1,
						1,
						1,
						1,
						1,
						1,
						1
					],
					"player_costs": [
						7200.0,
						3800.0,
						5400.0,
						5600.0,
						7000.0,
						3600.0,
						5300.0,
						9300.0
					],
					"player_costs_multiplier": [
						1,
						1,
						1,
						1,
						1,
						1,
						1,
						1
					],
					"team_ids": [
						24
					],
					"team_fpts": [
						18.0
					],
					"team_fpts_multiplier": [
						1
					],
					"team_costs": [
						2700.0
					],
					"team_costs_multiplier": [
						1
					],
					"placement_percentile": null
				},
				"wagered_outcome": {
					"total_score": 146.54129728042918,
					"total_cost": 50000.0,
					"player_ids": [
						265,
						349,
						465,
						47,
						291,
						364,
						53,
						383
					],
					"player_fpts": [
						13.507100435409058,
						23.033578245712853,
						15.947556247700199,
						11.717540540610727,
						15.84880666321669,
						16.982310097428407,
						22.34780286527003,
						18.803551445773905
					],
					"player_fpts_multiplier": [
						1,
						1,
						1,
						1,
						1,
						1,
						1,
						1
					],
					"player_costs": [
						5900.0,
						7900.0,
						5000.0,
						4000.0,
						4600.0,
						7000.0,
						5400.0,
						7700.0
					],
					"player_costs_multiplier": [
						1,
						1,
						1,
						1,
						1,
						1,
						1,
						1
					],
					"team_ids": [
						18
					],
					"team_fpts": [
						8.35305073930729
					],
					"team_fpts_multiplier": [
						1
					],
					"team_costs": [
						2500.0
					],
					"team_costs_multiplier": [
						1
					],
					"placement_percentile": 0.6075182402292961
				},
				"predicted_score": 138.18824654112188,
				"final_player_fpts": [
					13.0,
					20.6,
					4.300000000000001,
					1.8,
					15.5,
					10.2,
					15.120000000000001,
					3.8
				],
				"final_team_fpts": [
					8.0
				]
			},
			{
				"strategy_name": "C_5050_1",
				"wager": 1,
				"bet_return": 1.8,
				"slate_name": "Main",
				"slate_info": {
					"style": "CLASSIC",
					"games": [
						179,
						189,
						190,
						180,
						181,
						178,
						184,
						192,
						185,
						182,
						191,
						186,
						183,
						187,
						188,
						177
					],
					"slate_id": 33,
					"name": "Main"
				},
				"actual_outcome": {
					"total_score": 283.78000000000003,
					"total_cost": 49900.0,
					"player_ids": [
						220,
						261,
						120,
						162,
						215,
						22,
						31,
						372
					],
					"player_fpts": [
						36.8,
						29.700000000000003,
						31.9,
						34.64,
						39.8,
						24.7,
						33.74,
						34.5
					],
					"player_fpts_multiplier": [
						1,
						1,
						1,
						1,
						1,
						1,
						1,
						1
					],
					"player_costs": [
						7200.0,
						3800.0,
						5400.0,
						5600.0,
						7000.0,
						3600.0,
						5300.0,
						9300.0
					],
					"player_costs_multiplier": [
						1,
						1,
						1,
						1,
						1,
						1,
						1,
						1
					],
					"team_ids": [
						24
					],
					"team_fpts": [
						18.0
					],
					"team_fpts_multiplier": [
						1
					],
					"team_costs": [
						2700.0
					],
					"team_costs_multiplier": [
						1
					],
					"placement_percentile": null
				},
				"wagered_outcome": {
					"total_score": 146.54129728042918,
					"total_cost": 50000.0,
					"player_ids": [
						265,
						349,
						465,
						47,
						291,
						364,
						53,
						383
					],
					"player_fpts": [
						13.507100435409058,
						23.033578245712853,
						15.947556247700199,
						11.717540540610727,
						15.84880666321669,
						16.982310097428407,
						22.34780286527003,
						18.803551445773905
					],
					"player_fpts_multiplier": [
						1,
						1,
						1,
						1,
						1,
						1,
						1,
						1
					],
					"player_costs": [
						5900.0,
						7900.0,
						5000.0,
						4000.0,
						4600.0,
						7000.0,
						5400.0,
						7700.0
					],
					"player_costs_multiplier": [
						1,
						1,
						1,
						1,
						1,
						1,
						1,
						1
					],
					"team_ids": [
						18
					],
					"team_fpts": [
						8.35305073930729
					],
					"team_fpts_multiplier": [
						1
					],
					"team_costs": [
						2500.0
					],
					"team_costs_multiplier": [
						1
					],
					"placement_percentile": 0.6075182402292961
				},
				"predicted_score": 138.18824654112188,
				"final_player_fpts": [
					13.0,
					20.6,
					4.300000000000001,
					1.8,
					15.5,
					10.2,
					15.120000000000001,
					3.8
				],
				"final_team_fpts": [
					8.0
				]
			}
		],
		[
			{
				"strategy_name": "C_gpp_25",
				"wager": 0.25,
				"bet_return": 0,
				"slate_name": "Main",
				"slate_info": {
					"style": "CLASSIC",
					"games": [
						193,
						208,
						194,
						197,
						196,
						204,
						198,
						195,
						201,
						200,
						202,
						207,
						205,
						199,
						206,
						203
					],
					"slate_id": 34,
					"name": "Main"
				},
				"actual_outcome": {
					"total_score": 302.3,
					"total_cost": 49200.0,
					"player_ids": [
						265,
						371,
						252,
						240,
						302,
						53,
						63,
						84
					],
					"player_fpts": [
						34.0,
						49.7,
						27.5,
						50.8,
						24.700000000000003,
						30.400000000000002,
						34.2,
						33.0
					],
					"player_fpts_multiplier": [
						1,
						1,
						1,
						1,
						1,
						1,
						1,
						1
					],
					"player_costs": [
						5500.0,
						6600.0,
						4100.0,
						3600.0,
						4800.0,
						5600.0,
						8600.0,
						8200.0
					],
					"player_costs_multiplier": [
						1,
						1,
						1,
						1,
						1,
						1,
						1,
						1
					],
					"team_ids": [
						14
					],
					"team_fpts": [
						18.0
					],
					"team_fpts_multiplier": [
						1
					],
					"team_costs": [
						2200.0
					],
					"team_costs_multiplier": [
						1
					],
					"placement_percentile": null
				},
				"wagered_outcome": {
					"total_score": 144.5793037266145,
					"total_cost": 49900.0,
					"player_ids": [
						220,
						465,
						645,
						45,
						215,
						364,
						246,
						63
					],
					"player_fpts": [
						19.107287811498736,
						14.387668326822611,
						13.370002644029263,
						21.78770058791168,
						18.980523609266463,
						16.54361527809133,
						11.63965524400043,
						21.554474712207046
					],
					"player_fpts_multiplier": [
						1,
						1,
						1,
						1,
						1,
						1,
						1,
						1
					],
					"player_costs": [
						7400.0,
						4600.0,
						3800.0,
						5700.0,
						6700.0,
						6800.0,
						4000.0,
						8600.0
					],
					"player_costs_multiplier": [
						1,
						1,
						1,
						1,
						1,
						1,
						1,
						1
					],
					"team_ids": [
						1
					],
					"team_fpts": [
						7.2083755127869535
					],
					"team_fpts_multiplier": [
						1
					],
					"team_costs": [
						2300.0
					],
					"team_costs_multiplier": [
						1
					],
					"placement_percentile": 0.5626639050674808
				},
				"predicted_score": 137.37092821382757,
				"final_player_fpts": [
					18.8,
					9.3,
					10.600000000000001,
					19.58,
					20.7,
					5.2,
					2.0,
					34.2
				],
				"final_team_fpts": [
					4.0
				]
			},
			{
				"strategy_name": "C_5050_1",
				"wager": 1,
				"bet_return": 1.8,
				"slate_name": "Main",
				"slate_info": {
					"style": "CLASSIC",
					"games": [
						193,
						208,
						194,
						197,
						196,
						204,
						198,
						195,
						201,
						200,
						202,
						207,
						205,
						199,
						206,
						203
					],
					"slate_id": 34,
					"name": "Main"
				},
				"actual_outcome": {
					"total_score": 302.3,
					"total_cost": 49200.0,
					"player_ids": [
						265,
						371,
						252,
						240,
						302,
						53,
						63,
						84
					],
					"player_fpts": [
						34.0,
						49.7,
						27.5,
						50.8,
						24.700000000000003,
						30.400000000000002,
						34.2,
						33.0
					],
					"player_fpts_multiplier": [
						1,
						1,
						1,
						1,
						1,
						1,
						1,
						1
					],
					"player_costs": [
						5500.0,
						6600.0,
						4100.0,
						3600.0,
						4800.0,
						5600.0,
						8600.0,
						8200.0
					],
					"player_costs_multiplier": [
						1,
						1,
						1,
						1,
						1,
						1,
						1,
						1
					],
					"team_ids": [
						14
					],
					"team_fpts": [
						18.0
					],
					"team_fpts_multiplier": [
						1
					],
					"team_costs": [
						2200.0
					],
					"team_costs_multiplier": [
						1
					],
					"placement_percentile": null
				},
				"wagered_outcome": {
					"total_score": 144.5793037266145,
					"total_cost": 49900.0,
					"player_ids": [
						220,
						465,
						645,
						45,
						215,
						364,
						246,
						63
					],
					"player_fpts": [
						19.107287811498736,
						14.387668326822611,
						13.370002644029263,
						21.78770058791168,
						18.980523609266463,
						16.54361527809133,
						11.63965524400043,
						21.554474712207046
					],
					"player_fpts_multiplier": [
						1,
						1,
						1,
						1,
						1,
						1,
						1,
						1
					],
					"player_costs": [
						7400.0,
						4600.0,
						3800.0,
						5700.0,
						6700.0,
						6800.0,
						4000.0,
						8600.0
					],
					"player_costs_multiplier": [
						1,
						1,
						1,
						1,
						1,
						1,
						1,
						1
					],
					"team_ids": [
						1
					],
					"team_fpts": [
						7.2083755127869535
					],
					"team_fpts_multiplier": [
						1
					],
					"team_costs": [
						2300.0
					],
					"team_costs_multiplier": [
						1
					],
					"placement_percentile": 0.5626639050674808
				},
				"predicted_score": 137.37092821382757,
				"final_player_fpts": [
					18.8,
					9.3,
					10.600000000000001,
					19.58,
					20.7,
					5.2,
					2.0,
					34.2
				],
				"final_team_fpts": [
					4.0
				]
			}
		],
		[
			{
				"strategy_name": "C_gpp_25",
				"wager": 0.25,
				"bet_return": 0,
				"slate_name": "Main",
				"slate_info": {
					"style": "CLASSIC",
					"games": [
						210,
						211,
						212,
						223,
						215,
						222,
						213,
						216,
						214,
						218,
						220,
						224,
						221,
						217,
						219,
						209
					],
					"slate_id": 35,
					"name": "Main"
				},
				"actual_outcome": {
					"total_score": 258.28,
					"total_cost": 49900.0,
					"player_ids": [
						295,
						231,
						240,
						271,
						281,
						386,
						106,
						372
					],
					"player_fpts": [
						39.0,
						36.5,
						33.24,
						32.3,
						14.100000000000001,
						25.040000000000003,
						23.7,
						34.4
					],
					"player_fpts_multiplier": [
						1,
						1,
						1,
						1,
						1,
						1,
						1,
						1
					],
					"player_costs": [
						8200.0,
						4100.0,
						5000.0,
						6500.0,
						2500.0,
						6100.0,
						5300.0,
						9500.0
					],
					"player_costs_multiplier": [
						1,
						1,
						1,
						1,
						1,
						1,
						1,
						1
					],
					"team_ids": [
						32
					],
					"team_fpts": [
						20.0
					],
					"team_fpts_multiplier": [
						1
					],
					"team_costs": [
						2700.0
					],
					"team_costs_multiplier": [
						1
					],
					"placement_percentile": null
				},
				"wagered_outcome": {
					"total_score": 143.74323638914026,
					"total_cost": 50000.0,
					"player_ids": [
						157,
						209,
						645,
						69,
						47,
						185,
						195,
						215
					],
					"player_fpts": [
						9.49468447956361,
						25.468266938935304,
						14.213465871467884,
						22.9024573207437,
						11.054930826988413,
						17.374624345250027,
						18.375321507452917,
						18.618620943116966
					],
					"player_fpts_multiplier": [
						1,
						1,
						1,
						1,
						1,
						1,
						1,
						1
					],
					"player_costs": [
						3500.0,
						6900.0,
						4600.0,
						8700.0,
						3900.0,
						6100.0,
						6800.0,
						7400.0
					],
					"player_costs_multiplier": [
						1,
						1,
						1,
						1,
						1,
						1,
						1,
						1
					],
					"team_ids": [
						19
					],
					"team_fpts": [
						6.240864155621447
					],
					"team_fpts_multiplier": [
						1
					],
					"team_costs": [
						2100.0
					],
					"team_costs_multiplier": [
						1
					],
					"placement_percentile": 0.6547533292147157
				},
				"predicted_score": 137.50237223351883,
				"final_player_fpts": [
					2.9,
					18.02,
					3.6000000000000005,
					26.0,
					10.8,
					30.0,
					13.5,
					13.100000000000001
				],
				"final_team_fpts": [
					6.0
				]
			},
			{
				"strategy_name": "C_5050_1",
				"wager": 1,
				"bet_return": 1.8,
				"slate_name": "Main",
				"slate_info": {
					"style": "CLASSIC",
					"games": [
						210,
						211,
						212,
						223,
						215,
						222,
						213,
						216,
						214,
						218,
						220,
						224,
						221,
						217,
						219,
						209
					],
					"slate_id": 35,
					"name": "Main"
				},
				"actual_outcome": {
					"total_score": 258.28,
					"total_cost": 49900.0,
					"player_ids": [
						231,
						295,
						240,
						271,
						281,
						386,
						106,
						372
					],
					"player_fpts": [
						36.5,
						39.0,
						33.24,
						32.3,
						14.100000000000001,
						25.040000000000003,
						23.7,
						34.4
					],
					"player_fpts_multiplier": [
						1,
						1,
						1,
						1,
						1,
						1,
						1,
						1
					],
					"player_costs": [
						4100.0,
						8200.0,
						5000.0,
						6500.0,
						2500.0,
						6100.0,
						5300.0,
						9500.0
					],
					"player_costs_multiplier": [
						1,
						1,
						1,
						1,
						1,
						1,
						1,
						1
					],
					"team_ids": [
						32
					],
					"team_fpts": [
						20.0
					],
					"team_fpts_multiplier": [
						1
					],
					"team_costs": [
						2700.0
					],
					"team_costs_multiplier": [
						1
					],
					"placement_percentile": null
				},
				"wagered_outcome": {
					"total_score": 143.74323638914026,
					"total_cost": 50000.0,
					"player_ids": [
						157,
						209,
						645,
						69,
						47,
						185,
						195,
						215
					],
					"player_fpts": [
						9.49468447956361,
						25.468266938935304,
						14.213465871467884,
						22.9024573207437,
						11.054930826988413,
						17.374624345250027,
						18.375321507452917,
						18.618620943116966
					],
					"player_fpts_multiplier": [
						1,
						1,
						1,
						1,
						1,
						1,
						1,
						1
					],
					"player_costs": [
						3500.0,
						6900.0,
						4600.0,
						8700.0,
						3900.0,
						6100.0,
						6800.0,
						7400.0
					],
					"player_costs_multiplier": [
						1,
						1,
						1,
						1,
						1,
						1,
						1,
						1
					],
					"team_ids": [
						19
					],
					"team_fpts": [
						6.240864155621447
					],
					"team_fpts_multiplier": [
						1
					],
					"team_costs": [
						2100.0
					],
					"team_costs_multiplier": [
						1
					],
					"placement_percentile": 0.6547533292147157
				},
				"predicted_score": 137.50237223351883,
				"final_player_fpts": [
					2.9,
					18.02,
					3.6000000000000005,
					26.0,
					10.8,
					30.0,
					13.5,
					13.100000000000001
				],
				"final_team_fpts": [
					6.0
				]
			}
		]
	],
	"bt_notes": [
		[],
		[],
		[],
		[],
		[],
		[],
		[],
		[],
		[],
		[],
		[]
	],
	"dbfile": "nfl_2018.db",
	"sport": "nfl",
	"service": "draftkings",
	"strategies_filepath": null,
	"strategies": [
		"C_gpp_25",
		"C_5050_1",
		"SD_5050_1",
		"SD_gpp_25"
	]
}